zapit/__init__.py
zapit/exceptions.py
zapit/models/network.py
zapit/models/network_member.py
zapit/models/organizations.py
zapit/models/user.py
zapit/models/util.py
zapit/requestor.py
zapit/zapit.py
zapit-0.1.1.dist-info/METADATA
zapit-0.1.1.dist-info/WHEEL
zapit-0.1.1.dist-info/RECORD
