Metadata-Version: 2.1
Name: zapit
Version: 0.1.1
Summary: A Zerotier API wrapper.
License: MIT
Author: Macleay Stephenson
Author-email: macleays@gmail.com
Requires-Python: >=3.8,<4.0
Classifier: License :: OSI Approved :: MIT License
Classifier: Programming Language :: Python :: 3
Classifier: Programming Language :: Python :: 3.8
Classifier: Programming Language :: Python :: 3.9
Classifier: Programming Language :: Python :: 3.10
Classifier: Programming Language :: Python :: 3.11
Requires-Dist: betamax (>=0.8.1,<0.9.0)
Requires-Dist: pydantic (>=1.6.2)
Requires-Dist: requests (>=2.28.2,<3.0.0)
